Metadata-Version: 1.0
Name: distributions-Gauss-Bino
Version: 0.1
Summary: Gaussian distributions & Binomial
Home-page: UNKNOWN
Author: Shailendra Kumar
Author-email: sckumarpy@gmail.com
License: UNKNOWN
Platform: UNKNOWN
